mite_schema/__init__.py
mite_schema/main.py
mite_schema/schema/entry.json
mite_schema/schema_manager/__init__.py
mite_schema/schema_manager/schema_manager.py
mite_schema-1.8.3.dist-info/METADATA
mite_schema-1.8.3.dist-info/WHEEL
mite_schema-1.8.3.dist-info/entry_points.txt
mite_schema-1.8.3.dist-info/licenses/LICENSE
mite_schema-1.8.3.dist-info/RECORD
