Metadata-Version: 2.4
Name: mite_schema
Version: 1.8.3
Summary: Containing the Minimum Information about a Tailoring Enzymes data standard schema and auxiliary methods
Project-URL: Website, https://mite.bioinformatics.nl/
Project-URL: Homepage, https://github.com/mite-standard/mite_schema
Project-URL: Issues, https://github.com/mite-standard/mite_schema/issues
Project-URL: Discussions, https://github.com/orgs/mite-standard/discussions/3
Author-email: "Mitja M. Zdouc" <zdoucmm@gmail.com>
License-File: LICENSE
Keywords: cheminformatics,genomics
Classifier: Development Status :: 4 - Beta
Classifier: License :: OSI Approved :: MIT License
Classifier: Operating System :: POSIX :: Linux
Classifier: Programming Language :: Python :: 3.11
Classifier: Programming Language :: Python :: 3.12
Classifier: Topic :: Scientific/Engineering :: Bio-Informatics
Classifier: Topic :: Scientific/Engineering :: Chemistry
Requires-Python: >=3.11
Requires-Dist: argparse~=1.4
Requires-Dist: coloredlogs~=15.0
Requires-Dist: jsonschema~=4.25
Requires-Dist: pydantic~=2.11
Provides-Extra: dev
Requires-Dist: pre-commit~=4.3; extra == 'dev'
Requires-Dist: pytest~=8.4; extra == 'dev'
Requires-Dist: ruff~=0.13; extra == 'dev'
